pygwasvcf/__init__.py
pygwasvcf/gwas_vcf.py
pygwasvcf/variant_record_gwas_funs.py
tests/__init__.py
tests/test_gwas_file.py
tests/test_variant_record_gwas_funs.py
pygwasvcf-0.0.4.dist-info/LICENSE
pygwasvcf-0.0.4.dist-info/METADATA
pygwasvcf-0.0.4.dist-info/WHEEL
pygwasvcf-0.0.4.dist-info/top_level.txt
pygwasvcf-0.0.4.dist-info/RECORD
