Metadata-Version: 2.1
Name: pygwasvcf
Version: 0.0.4
Summary: A package for reading GWAS summary statistics stored in VCF/BCF format
Home-page: https://github.com/MRCIEU/pygwasvcf
Author: Matt Lyon
Author-email: ml18692@bristol.ac.uk
License: UNKNOWN
Platform: UNKNOWN
Classifier: Programming Language :: Python :: 3
Classifier: License :: OSI Approved :: MIT License
Classifier: Operating System :: OS Independent
Requires-Python: >=3.6
License-File: LICENSE
Requires-Dist: pysam
Requires-Dist: pytest
